TestingLibrarySelectorsPlugin
