Metadata-Version: 2.1
Name: rf-se-dtl-selectors-plugin
Version: 0.4.1
Summary: DOM testing library inspired selectors for Robot Framework SeleniumLibrary.
Home-page: https://github.com/kangasta/rf-se-dtl-selectors-plugin
Author: Toni Kangas
License: UNKNOWN
Platform: UNKNOWN
Classifier: Programming Language :: Python :: 3
Classifier: License :: OSI Approved :: MIT License
Classifier: Operating System :: OS Independent
Requires-Python: >=3.6
